tensorflow_k8s/__init__.py
tensorflow_k8s-0.0.2.dist-info/LICENSE
tensorflow_k8s-0.0.2.dist-info/METADATA
tensorflow_k8s-0.0.2.dist-info/WHEEL
tensorflow_k8s-0.0.2.dist-info/top_level.txt
tensorflow_k8s-0.0.2.dist-info/RECORD
