Metadata-Version: 2.1
Name: tensorflow-k8s
Version: 0.0.2
Summary: Tensorflow serving extension
Home-page: https://pypi.org/project/tensorflow_k8s
Author: Kundjanasith Thonglek
Author-email: kundjanasith.t@Ku.th
License: UNKNOWN
Platform: UNKNOWN
Classifier: Programming Language :: Python :: 3
Classifier: License :: OSI Approved :: Academic Free License (AFL)
Classifier: Operating System :: OS Independent
